gpp_py_component/__init__.py
gpp_py_component/aes.py
gpp_py_component/constant.py
gpp_py_component/dbConfig.py
gpp_py_component/handleData.py
gpp_py_component/lazyImport.py
gpp_py_component/response.py
gpp_py_component/sendMail.py
gpp_py_component-0.1.3.dist-info/LICENSE
gpp_py_component-0.1.3.dist-info/METADATA
gpp_py_component-0.1.3.dist-info/WHEEL
gpp_py_component-0.1.3.dist-info/top_level.txt
gpp_py_component-0.1.3.dist-info/RECORD
