Metadata-Version: 2.1
Name: gpp-py-component
Version: 0.1.3
Summary: for internal use
Author: L
License: MIT Licence
License-File: LICENSE
Requires-Dist: crypto
Requires-Dist: django
Requires-Dist: cx-Oracle
Requires-Dist: pandas
Requires-Dist: jsonpath
